migrator_tool/__init__.py
migrator_tool/migrator_tool.py
tests/__init__.py
tests/test_migrator.py
migrator_tool-1.0.2.dist-info/LICENSE
migrator_tool-1.0.2.dist-info/METADATA
migrator_tool-1.0.2.dist-info/WHEEL
migrator_tool-1.0.2.dist-info/entry_points.txt
migrator_tool-1.0.2.dist-info/top_level.txt
migrator_tool-1.0.2.dist-info/RECORD
