Metadata-Version: 2.2
Name: migrator-tool
Version: 1.0.2
Summary: A tool to migrate SQLite (.csdb) data to MySQL with a user-friendly GUI.
Home-page: https://github.com/ndayiz/migrator_tool
Author: NISR IT TEAM
Author-email: ndayizeye.bernard@statistics.gov.rw
License: NISR
Classifier: Programming Language :: Python :: 3
Classifier: License :: OSI Approved :: MIT License
Classifier: Operating System :: OS Independent
Requires-Python: >=3.7
License-File: LICENSE
Requires-Dist: customtkinter
Requires-Dist: mysql-connector-python
Dynamic: author
Dynamic: author-email
Dynamic: classifier
Dynamic: description
Dynamic: description-content-type
Dynamic: home-page
Dynamic: license
Dynamic: requires-dist
Dynamic: requires-python
Dynamic: summary
